parsera_pieces/__init__.py
parsera_pieces/main.py
parsera_pieces/page.py
parsera_pieces/utils.py
parsera_pieces/engine/__init__.py
parsera_pieces/engine/model.py
parsera_pieces/engine/simple_extractor.py
parsera_pieces-0.0.6.dist-info/LICENSE
parsera_pieces-0.0.6.dist-info/METADATA
parsera_pieces-0.0.6.dist-info/WHEEL
parsera_pieces-0.0.6.dist-info/top_level.txt
parsera_pieces-0.0.6.dist-info/RECORD
