Metadata-Version: 2.1
Name: parsera-pieces
Version: 0.0.6
Summary: Fork of the original Parsera Lightweight library for scraping web-sites with Pieces QGPT LLM
Home-page: https://github.com/pieces-app/parsera-pieces
Author: Shivay at Pieces
Author-email: shivay@pieces.app
Classifier: Development Status :: 3 - Alpha
Classifier: Intended Audience :: Developers
Classifier: License :: OSI Approved :: GNU General Public License v2 or later (GPLv2+)
Classifier: Operating System :: OS Independent
Classifier: Programming Language :: Python :: 3
Classifier: Programming Language :: Python :: 3.10
Requires-Python: >=3.10
License-File: LICENSE
Requires-Dist: langchain (>=0.2.6)
Requires-Dist: langchain-openai (>=0.1.8)
Requires-Dist: playwright (>=1.44.0)
Requires-Dist: playwright-stealth (>=1.0.6)
Requires-Dist: markdownify (>=0.12.1)
Requires-Dist: pieces-copilot-sdk (>=0.5.0)
Requires-Dist: parsera (>=0.1.3)
